clarin/__init__.py
clarin/sru/__init__.py
clarin/sru/constants.py
clarin/sru/diagnostic.py
clarin/sru/exception.py
clarin/sru/py.typed
clarin/sru/queryparser.py
clarin/sru/server/__init__.py
clarin/sru/server/auth.py
clarin/sru/server/config.py
clarin/sru/server/request.py
clarin/sru/server/result.py
clarin/sru/server/server.py
clarin/sru/server/wsgi.py
clarin/sru/xml/__init__.py
clarin/sru/xml/sru-server-config.xsd
clarin/sru/xml/writer.py
clarin/sru/xml/xml.xsd
fcs_sru_server-1.1.3.dist-info/METADATA
fcs_sru_server-1.1.3.dist-info/WHEEL
fcs_sru_server-1.1.3.dist-info/top_level.txt
fcs_sru_server-1.1.3.dist-info/zip-safe
fcs_sru_server-1.1.3.dist-info/RECORD
