Metadata-Version: 2.1
Name: fcs-sru-server
Version: 1.1.3
Summary: "FCS SRU Server"
Home-page: https://github.com/Querela/fcs-sru-server-python/
Author: Erik Körner
Author-email: "Erik Körner" <koerner@saw-leipzig.de>
License: MIT
Project-URL: Source, https://github.com/Querela/fcs-sru-server-python/
Project-URL: Documentation, https://fcs-sru-server-python.readthedocs.io/
Project-URL: Issue Tracker, https://github.com/Querela/fcs-sru-server-python/issues
Keywords: SRU,FCS,CLARIN
Requires-Python: >=3.8
Requires-Dist: lxml >=4.9.2
Requires-Dist: werkzeug >=2.2.2
Requires-Dist: cql-parser >=1.0.2
Provides-Extra: build
Requires-Dist: build >=0.10.0 ; extra == 'build'
Requires-Dist: twine >=4.0.2 ; extra == 'build'
Provides-Extra: docs
Requires-Dist: sphinx >=5.3.0 ; extra == 'docs'
Requires-Dist: sphinx-rtd-theme >=0.5.1 ; extra == 'docs'
Requires-Dist: myst-parser >=0.18.1 ; extra == 'docs'
Provides-Extra: style
Requires-Dist: black >=23.1.0 ; extra == 'style'
Requires-Dist: flake8 >=6.0.0 ; extra == 'style'
Requires-Dist: isort >=5.11.4 ; extra == 'style'
Requires-Dist: mypy >=0.991 ; extra == 'style'
Requires-Dist: darglint >=1.8.1 ; extra == 'style'
Provides-Extra: test
Requires-Dist: pytest >=7.2.1 ; extra == 'test'
Requires-Dist: pytest-cov >=4.0.0 ; extra == 'test'
Requires-Dist: pytest-clarity >=1.0.1 ; extra == 'test'
Requires-Dist: pytest-randomly >=3.12.0 ; extra == 'test'
